vagen/__init__.py
vagen/hilevelmod.py
vagen/veriloga.py
vagen-1.0.0.dist-info/LICENSE
vagen-1.0.0.dist-info/METADATA
vagen-1.0.0.dist-info/WHEEL
vagen-1.0.0.dist-info/top_level.txt
vagen-1.0.0.dist-info/RECORD
