Metadata-Version: 2.2
Name: vagen
Version: 1.0.0
Summary: Generates verilogA testbench for verification of analog IPs (VLSI design)
Author-email: Rodrigo Pedroso Mendes <roedroso@gmail.com>
Project-URL: Homepage, https://github.com/rpm2003rpm/vagen
Classifier: Programming Language :: Python :: 3
Classifier: License :: OSI Approved :: MIT License
Classifier: Operating System :: OS Independent
Requires-Python: >=3.7
License-File: LICENSE
Requires-Dist: regex>=2023.6.3
Requires-Dist: datetime>=5.2
